[
  {
    "id": 26,
    "title": "Remove Duplicates from Sorted Array",
    "title_slug": "remove-duplicates-from-sorted-array",
    "difficulty": "Easy",
    "skills": [
      "Array",
      "Two Pointers"
    ]
  },
  {
    "id": 234,
    "title": "Palindrome Linked List",
    "title_slug": "palindrome-linked-list",
    "difficulty": "Easy",
    "skills": [
      "Linked List",
      "Recursion",
      "Stack",
      "Two Pointers"
    ]
  },
  {
    "id": 237,
    "title": "Delete Node in a Linked List",
    "title_slug": "delete-node-in-a-linked-list",
    "difficulty": "Medium",
    "skills": [
      "Linked List"
    ]
  },
  {
    "id": 1480,
    "title": "Running Sum of 1d Array",
    "title_slug": "running-sum-of-1d-array",
    "difficulty": "Easy",
    "skills": [
      "Array",
      "Prefix Sum"
    ]
  },
  {
    "id": 1920,
    "title": "Build Array from Permutation",
    "title_slug": "build-array-from-permutation",
    "difficulty": "Easy",
    "skills": [
      "Array",
      "Simulation"
    ]
  }
]